bruno_util/__init__.py
bruno_util/cached_property.py
bruno_util/exampleSimpleMapReduce.py
bruno_util/math.py
bruno_util/multiprocessing_mapreduce.py
bruno_util/pandas_util.py
bruno_util/path.py
bruno_util/pickle_variables.py
bruno_util/plotting.py
bruno_util/random.py
bruno_util/runge_kutta.py
bruno_util/utils.py
bruno_util/mittag_leffler/__init__.py
bruno_util/mittag_leffler/mittag_leffler.py
bruno_util/mittag_leffler/ml_internal.py
bruno_util/mittag_leffler/test_ml.py
bruno_util-1.5.0.dist-info/LICENSE
bruno_util-1.5.0.dist-info/METADATA
bruno_util-1.5.0.dist-info/WHEEL
bruno_util-1.5.0.dist-info/top_level.txt
bruno_util-1.5.0.dist-info/RECORD
