Metadata-Version: 2.1
Name: bruno-util
Version: 1.5.0
Summary: Catch-all package for utilities useful to Bruno Beltran
Home-page: https://github.com/brunobeltran/bruno_util
Author: Bruno Beltran
Author-email: brunobeltran0@gmail.com
License: MIT
Keywords: parameter scanning scientific search testing
Platform: UNKNOWN
Classifier: Development Status :: 2 - Pre-Alpha
Classifier: Intended Audience :: Developers
Classifier: Intended Audience :: Science/Research
Classifier: License :: OSI Approved :: MIT License
Classifier: Topic :: Utilities
Requires-Dist: pandas
Requires-Dist: numpy
Requires-Dist: matplotlib
Requires-Dist: numba
Requires-Dist: seaborn
Requires-Dist: pscan
Requires-Dist: multi-locus-analysis
